shadermake/__init__.py
shadermake/decorator.py
shadermake/engine.py
shadermake/engines/opengl.py
shadermake-0.0.5.dist-info/LICENSE
shadermake-0.0.5.dist-info/METADATA
shadermake-0.0.5.dist-info/WHEEL
shadermake-0.0.5.dist-info/top_level.txt
shadermake-0.0.5.dist-info/RECORD
