Metadata-Version: 2.1
Name: shadermake
Version: 0.0.5
Summary: Transforming python code to GLSL shaders.
Home-page: https://github.com/EngDrom/ShaderMake
Author: EngDrom project
Author-email: <engdrom.project@gmail.com>
License: UNKNOWN
Keywords: python,opengl,glsl
Platform: UNKNOWN
Classifier: Development Status :: 1 - Planning
Classifier: Intended Audience :: Developers
Classifier: Programming Language :: Python :: 3
Classifier: Operating System :: Unix
Classifier: Operating System :: MacOS :: MacOS X
Classifier: Operating System :: Microsoft :: Windows
License-File: LICENSE
